<archimate:ArchimateDiagramModel
    xmlns:xsi="http://www.w3.org/2001/XMLSchema-instance"
    xmlns:archimate="http://www.archimatetool.com/archimate"
    name="LP027 - Services de production mutualisés"
    id="0b2efdc6">
  <children
      xsi:type="archimate:DiagramModelArchimateObject"
      id="1ff82859"
      targetConnections="a3b13df2"
      type="1">
    <bounds
        x="60"
        y="36"
        width="157"
        height="55"/>
    <archimateElement
        xsi:type="archimate:BusinessService"
        href="BusinessService_b8b441b6.xml#b8b441b6"/>
  </children>
  <children
      xsi:type="archimate:DiagramModelArchimateObject"
      id="10bdce1a"
      type="1">
    <bounds
        x="60"
        y="120"
        width="157"
        height="55"/>
    <archimateElement
        xsi:type="archimate:BusinessService"
        href="BusinessService_d3f5571c.xml#d3f5571c"/>
  </children>
  <children
      xsi:type="archimate:DiagramModelArchimateObject"
      id="a5266813"
      type="1">
    <bounds
        x="60"
        y="204"
        width="157"
        height="55"/>
    <archimateElement
        xsi:type="archimate:BusinessService"
        href="BusinessService_12095f3d.xml#12095f3d"/>
  </children>
  <children
      xsi:type="archimate:DiagramModelArchimateObject"
      id="be8290bd"
      targetConnections="361d21f4">
    <sourceConnections
        xsi:type="archimate:DiagramModelArchimateConnection"
        id="a3b13df2"
        source="be8290bd"
        target="1ff82859">
      <archimateRelationship
          xsi:type="archimate:RealizationRelationship"
          href="RealizationRelationship_5a4ed8bd.xml#5a4ed8bd"/>
    </sourceConnections>
    <bounds
        x="288"
        y="36"
        width="120"
        height="55"/>
    <archimateElement
        xsi:type="archimate:ApplicationComponent"
        href="ApplicationComponent_2ddd518b.xml#2ddd518b"/>
  </children>
  <children
      xsi:type="archimate:DiagramModelArchimateObject"
      id="71ed0257"
      targetConnections="960c8006"
      type="1">
    <bounds
        x="60"
        y="288"
        width="157"
        height="55"/>
    <archimateElement
        xsi:type="archimate:BusinessService"
        href="BusinessService_3856af95.xml#3856af95"/>
  </children>
  <children
      xsi:type="archimate:DiagramModelArchimateObject"
      id="987b156a">
    <sourceConnections
        xsi:type="archimate:DiagramModelArchimateConnection"
        id="361d21f4"
        source="987b156a"
        target="be8290bd">
      <archimateRelationship
          xsi:type="archimate:ServingRelationship"
          href="ServingRelationship_6e5a9ba1.xml#6e5a9ba1"/>
    </sourceConnections>
    <bounds
        x="492"
        y="36"
        width="120"
        height="55"/>
    <archimateElement
        xsi:type="archimate:SystemSoftware"
        href="SystemSoftware_a1293ad1.xml#a1293ad1"/>
  </children>
  <children
      xsi:type="archimate:DiagramModelArchimateObject"
      id="b3000490"
      targetConnections="794670b7">
    <sourceConnections
        xsi:type="archimate:DiagramModelArchimateConnection"
        id="960c8006"
        source="b3000490"
        target="71ed0257">
      <archimateRelationship
          xsi:type="archimate:RealizationRelationship"
          href="RealizationRelationship_02768184.xml#02768184"/>
    </sourceConnections>
    <bounds
        x="288"
        y="288"
        width="120"
        height="55"/>
    <archimateElement
        xsi:type="archimate:ApplicationComponent"
        href="ApplicationComponent_a00810dd.xml#a00810dd"/>
  </children>
  <children
      xsi:type="archimate:DiagramModelArchimateObject"
      id="282a305d">
    <sourceConnections
        xsi:type="archimate:DiagramModelArchimateConnection"
        id="794670b7"
        source="282a305d"
        target="b3000490">
      <archimateRelationship
          xsi:type="archimate:ServingRelationship"
          href="ServingRelationship_8203d6e9.xml#8203d6e9"/>
    </sourceConnections>
    <bounds
        x="492"
        y="288"
        width="120"
        height="55"/>
    <archimateElement
        xsi:type="archimate:SystemSoftware"
        href="SystemSoftware_8285d02c.xml#8285d02c"/>
  </children>
  <children
      xsi:type="archimate:DiagramModelArchimateObject"
      id="6e039a74"
      targetConnections="68d612f2">
    <sourceConnections
        xsi:type="archimate:DiagramModelArchimateConnection"
        id="562f057f"
        source="6e039a74"
        target="650afbe4">
      <archimateRelationship
          xsi:type="archimate:RealizationRelationship"
          href="RealizationRelationship_d7362546.xml#d7362546"/>
    </sourceConnections>
    <bounds
        x="288"
        y="444"
        width="120"
        height="55"/>
    <archimateElement
        xsi:type="archimate:ApplicationComponent"
        href="ApplicationComponent_5c35beb6.xml#5c35beb6"/>
  </children>
  <children
      xsi:type="archimate:DiagramModelArchimateObject"
      id="832ed889">
    <sourceConnections
        xsi:type="archimate:DiagramModelArchimateConnection"
        id="68d612f2"
        source="832ed889"
        target="6e039a74">
      <archimateRelationship
          xsi:type="archimate:ServingRelationship"
          href="ServingRelationship_f6eec8ff.xml#f6eec8ff"/>
    </sourceConnections>
    <sourceConnections
        xsi:type="archimate:DiagramModelArchimateConnection"
        id="14979fd1"
        source="832ed889"
        target="b031f8b6">
      <archimateRelationship
          xsi:type="archimate:CompositionRelationship"
          href="CompositionRelationship_eae18f2e.xml#eae18f2e"/>
    </sourceConnections>
    <sourceConnections
        xsi:type="archimate:DiagramModelArchimateConnection"
        id="0c4b4369"
        source="832ed889"
        target="de47c3b8">
      <archimateRelationship
          xsi:type="archimate:ServingRelationship"
          href="ServingRelationship_7764ad1c.xml#7764ad1c"/>
    </sourceConnections>
    <sourceConnections
        xsi:type="archimate:DiagramModelArchimateConnection"
        id="deccf4e0"
        source="832ed889"
        target="e2f1fc24">
      <archimateRelationship
          xsi:type="archimate:CompositionRelationship"
          href="CompositionRelationship_0ba48c96.xml#0ba48c96"/>
    </sourceConnections>
    <sourceConnections
        xsi:type="archimate:DiagramModelArchimateConnection"
        id="4e9952fa"
        source="832ed889"
        target="f2e39fcd">
      <archimateRelationship
          xsi:type="archimate:CompositionRelationship"
          href="CompositionRelationship_ea976637.xml#ea976637"/>
    </sourceConnections>
    <sourceConnections
        xsi:type="archimate:DiagramModelArchimateConnection"
        id="18b733f5"
        source="832ed889"
        target="433bb849">
      <archimateRelationship
          xsi:type="archimate:ServingRelationship"
          href="ServingRelationship_d0b86b51.xml#d0b86b51"/>
    </sourceConnections>
    <sourceConnections
        xsi:type="archimate:DiagramModelArchimateConnection"
        id="ab4b06d0"
        source="832ed889"
        target="10f147d1">
      <archimateRelationship
          xsi:type="archimate:ServingRelationship"
          href="ServingRelationship_8fd06d8c.xml#8fd06d8c"/>
    </sourceConnections>
    <bounds
        x="492"
        y="384"
        width="120"
        height="127"/>
    <archimateElement
        xsi:type="archimate:SystemSoftware"
        href="SystemSoftware_e07e33f6.xml#e07e33f6"/>
  </children>
  <children
      xsi:type="archimate:DiagramModelArchimateObject"
      id="650afbe4"
      targetConnections="562f057f"
      type="1">
    <bounds
        x="60"
        y="444"
        width="157"
        height="55"/>
    <archimateElement
        xsi:type="archimate:BusinessService"
        href="BusinessService_a15a3144.xml#a15a3144"/>
  </children>
  <children
      xsi:type="archimate:DiagramModelArchimateObject"
      id="b031f8b6"
      targetConnections="14979fd1">
    <sourceConnections
        xsi:type="archimate:DiagramModelArchimateConnection"
        id="e7acd01a"
        source="b031f8b6"
        target="a88f696d">
      <archimateRelationship
          xsi:type="archimate:ServingRelationship"
          href="ServingRelationship_81a79b75.xml#81a79b75"/>
    </sourceConnections>
    <bounds
        x="492"
        y="552"
        width="120"
        height="55"/>
    <archimateElement
        xsi:type="archimate:SystemSoftware"
        href="SystemSoftware_d49c551c.xml#d49c551c"/>
  </children>
  <children
      xsi:type="archimate:DiagramModelArchimateObject"
      id="a88f696d"
      targetConnections="e7acd01a">
    <sourceConnections
        xsi:type="archimate:DiagramModelArchimateConnection"
        id="13144db3"
        source="a88f696d"
        target="ad62812e">
      <archimateRelationship
          xsi:type="archimate:RealizationRelationship"
          href="RealizationRelationship_c9499abf.xml#c9499abf"/>
    </sourceConnections>
    <bounds
        x="288"
        y="552"
        width="120"
        height="55"/>
    <archimateElement
        xsi:type="archimate:ApplicationComponent"
        href="ApplicationComponent_74c4337b.xml#74c4337b"/>
  </children>
  <children
      xsi:type="archimate:DiagramModelArchimateObject"
      id="ad62812e"
      targetConnections="13144db3"
      type="1">
    <bounds
        x="60"
        y="552"
        width="157"
        height="55"/>
    <archimateElement
        xsi:type="archimate:BusinessService"
        href="BusinessService_3d7fa07e.xml#3d7fa07e"/>
  </children>
  <children
      xsi:type="archimate:DiagramModelArchimateObject"
      id="de47c3b8"
      targetConnections="0c4b4369">
    <sourceConnections
        xsi:type="archimate:DiagramModelArchimateConnection"
        id="e238087d"
        source="de47c3b8"
        target="d5165bdc">
      <archimateRelationship
          xsi:type="archimate:RealizationRelationship"
          href="RealizationRelationship_1d84c5ce.xml#1d84c5ce"/>
    </sourceConnections>
    <bounds
        x="288"
        y="372"
        width="120"
        height="55"/>
    <archimateElement
        xsi:type="archimate:ApplicationComponent"
        href="ApplicationComponent_dff5ed2f.xml#dff5ed2f"/>
  </children>
  <children
      xsi:type="archimate:DiagramModelArchimateObject"
      id="d5165bdc"
      targetConnections="e238087d"
      type="1">
    <bounds
        x="60"
        y="372"
        width="157"
        height="55"/>
    <archimateElement
        xsi:type="archimate:BusinessService"
        href="BusinessService_aeb372b4.xml#aeb372b4"/>
  </children>
  <children
      xsi:type="archimate:DiagramModelArchimateObject"
      id="e2f1fc24"
      targetConnections="deccf4e0">
    <sourceConnections
        xsi:type="archimate:DiagramModelArchimateConnection"
        id="ad340579"
        source="e2f1fc24"
        target="bbac9f8b">
      <archimateRelationship
          xsi:type="archimate:ServingRelationship"
          href="ServingRelationship_123a0082.xml#123a0082"/>
    </sourceConnections>
    <bounds
        x="648"
        y="552"
        width="120"
        height="55"/>
    <archimateElement
        xsi:type="archimate:SystemSoftware"
        href="SystemSoftware_8cc76bb8.xml#8cc76bb8"/>
  </children>
  <children
      xsi:type="archimate:DiagramModelArchimateObject"
      id="099b59e7"
      targetConnections="a4a6cf5d"
      type="1">
    <bounds
        x="960"
        y="552"
        width="157"
        height="55"/>
    <archimateElement
        xsi:type="archimate:BusinessService"
        href="BusinessService_d1195d5c.xml#d1195d5c"/>
  </children>
  <children
      xsi:type="archimate:DiagramModelArchimateObject"
      id="bbac9f8b"
      targetConnections="ad340579">
    <sourceConnections
        xsi:type="archimate:DiagramModelArchimateConnection"
        id="a4a6cf5d"
        source="bbac9f8b"
        target="099b59e7">
      <archimateRelationship
          xsi:type="archimate:RealizationRelationship"
          href="RealizationRelationship_3b3ca87d.xml#3b3ca87d"/>
    </sourceConnections>
    <bounds
        x="792"
        y="552"
        width="120"
        height="55"/>
    <archimateElement
        xsi:type="archimate:ApplicationComponent"
        href="ApplicationComponent_08a4e9f8.xml#08a4e9f8"/>
  </children>
  <children
      xsi:type="archimate:DiagramModelArchimateObject"
      id="f2e39fcd"
      targetConnections="4e9952fa">
    <sourceConnections
        xsi:type="archimate:DiagramModelArchimateConnection"
        id="a151b2ce"
        source="f2e39fcd"
        target="168de15d">
      <archimateRelationship
          xsi:type="archimate:ServingRelationship"
          href="ServingRelationship_9189820c.xml#9189820c"/>
    </sourceConnections>
    <bounds
        x="648"
        y="468"
        width="120"
        height="55"/>
    <archimateElement
        xsi:type="archimate:SystemSoftware"
        href="SystemSoftware_463d1160.xml#463d1160"/>
  </children>
  <children
      xsi:type="archimate:DiagramModelArchimateObject"
      id="168de15d"
      targetConnections="a151b2ce">
    <sourceConnections
        xsi:type="archimate:DiagramModelArchimateConnection"
        id="f1abfbb0"
        source="168de15d"
        target="590336e0">
      <archimateRelationship
          xsi:type="archimate:RealizationRelationship"
          href="RealizationRelationship_b0b3f10d.xml#b0b3f10d"/>
    </sourceConnections>
    <bounds
        x="792"
        y="468"
        width="120"
        height="55"/>
    <archimateElement
        xsi:type="archimate:ApplicationComponent"
        href="ApplicationComponent_6f169d94.xml#6f169d94"/>
  </children>
  <children
      xsi:type="archimate:DiagramModelArchimateObject"
      id="590336e0"
      targetConnections="f1abfbb0"
      type="1">
    <bounds
        x="960"
        y="468"
        width="157"
        height="55"/>
    <archimateElement
        xsi:type="archimate:BusinessService"
        href="BusinessService_91010729.xml#91010729"/>
  </children>
  <children
      xsi:type="archimate:DiagramModelArchimateObject"
      id="a24a1e12"
      targetConnections="a2055df6"
      type="1">
    <bounds
        x="960"
        y="398"
        width="157"
        height="55"/>
    <archimateElement
        xsi:type="archimate:BusinessService"
        href="BusinessService_4ca2f41c.xml#4ca2f41c"/>
  </children>
  <children
      xsi:type="archimate:DiagramModelArchimateObject"
      id="433bb849"
      targetConnections="18b733f5">
    <sourceConnections
        xsi:type="archimate:DiagramModelArchimateConnection"
        id="a2055df6"
        source="433bb849"
        target="a24a1e12">
      <archimateRelationship
          xsi:type="archimate:RealizationRelationship"
          href="RealizationRelationship_82da3d29.xml#82da3d29"/>
    </sourceConnections>
    <bounds
        x="792"
        y="398"
        width="120"
        height="55"/>
    <archimateElement
        xsi:type="archimate:ApplicationComponent"
        href="ApplicationComponent_fbb63d56.xml#fbb63d56"/>
  </children>
  <children
      xsi:type="archimate:DiagramModelArchimateObject"
      id="10f147d1"
      targetConnections="ab4b06d0">
    <sourceConnections
        xsi:type="archimate:DiagramModelArchimateConnection"
        id="297dfa68"
        source="10f147d1"
        target="edec0b0e">
      <archimateRelationship
          xsi:type="archimate:RealizationRelationship"
          href="RealizationRelationship_9074a28b.xml#9074a28b"/>
    </sourceConnections>
    <bounds
        x="792"
        y="318"
        width="120"
        height="55"/>
    <archimateElement
        xsi:type="archimate:ApplicationComponent"
        href="ApplicationComponent_3db82aaf.xml#3db82aaf"/>
  </children>
  <children
      xsi:type="archimate:DiagramModelArchimateObject"
      id="edec0b0e"
      targetConnections="297dfa68"
      type="1">
    <bounds
        x="960"
        y="318"
        width="157"
        height="55"/>
    <archimateElement
        xsi:type="archimate:BusinessService"
        href="BusinessService_658a0c84.xml#658a0c84"/>
  </children>
</archimate:ArchimateDiagramModel>
