<archimate:ArchimateDiagramModel
    xmlns:xsi="http://www.w3.org/2001/XMLSchema-instance"
    xmlns:archimate="http://www.archimatetool.com/archimate"
    name="M1 - Concevoir et lancer les produits &amp; services"
    id="84dc41c7"
    viewpoint="16">
  <children
      xsi:type="archimate:DiagramModelArchimateObject"
      id="ef680df5"
      targetConnections="9d1c5173 7958b4b8 c7f98e8f">
    <bounds
        x="480"
        y="60"
        width="120"
        height="559"/>
    <archimateElement
        xsi:type="archimate:BusinessProcess"
        href="BusinessProcess_acb569ab.xml#acb569ab"/>
  </children>
  <children
      xsi:type="archimate:DiagramModelArchimateObject"
      id="3df5a94c"
      targetConnections="57fa9dc0"
      type="1">
    <sourceConnections
        xsi:type="archimate:DiagramModelArchimateConnection"
        id="7958b4b8"
        source="3df5a94c"
        target="ef680df5">
      <archimateRelationship
          xsi:type="archimate:ServingRelationship"
          href="ServingRelationship_c0c15b76.xml#c0c15b76"/>
    </sourceConnections>
    <bounds
        x="672"
        y="60"
        width="120"
        height="55"/>
    <archimateElement
        xsi:type="archimate:BusinessService"
        href="BusinessService_35e9eeb2.xml#35e9eeb2"/>
  </children>
  <children
      xsi:type="archimate:DiagramModelArchimateObject"
      id="89c7be4e">
    <sourceConnections
        xsi:type="archimate:DiagramModelArchimateConnection"
        id="57fa9dc0"
        source="89c7be4e"
        target="3df5a94c">
      <archimateRelationship
          xsi:type="archimate:RealizationRelationship"
          href="RealizationRelationship_41e3e872.xml#41e3e872"/>
    </sourceConnections>
    <bounds
        x="864"
        y="60"
        width="120"
        height="55"/>
    <archimateElement
        xsi:type="archimate:ApplicationComponent"
        href="ApplicationComponent_2bb78953.xml#2bb78953"/>
  </children>
  <children
      xsi:type="archimate:DiagramModelArchimateObject"
      id="20e688a3"
      targetConnections="ec0ab06a dd404d33 4b42ea75 75bd4aeb c0c006b4 eb6c2190"
      type="1">
    <sourceConnections
        xsi:type="archimate:DiagramModelArchimateConnection"
        id="9d1c5173"
        source="20e688a3"
        target="ef680df5">
      <archimateRelationship
          xsi:type="archimate:ServingRelationship"
          href="ServingRelationship_0db441f5.xml#0db441f5"/>
    </sourceConnections>
    <bounds
        x="264"
        y="312"
        width="120"
        height="55"/>
    <archimateElement
        xsi:type="archimate:BusinessService"
        href="BusinessService_11abe9eb.xml#11abe9eb"/>
  </children>
  <children
      xsi:type="archimate:DiagramModelArchimateObject"
      id="bab02330"
      targetConnections="1603d18d">
    <sourceConnections
        xsi:type="archimate:DiagramModelArchimateConnection"
        id="ec0ab06a"
        source="bab02330"
        target="20e688a3">
      <archimateRelationship
          xsi:type="archimate:RealizationRelationship"
          href="RealizationRelationship_74e23873.xml#74e23873"/>
    </sourceConnections>
    <sourceConnections
        xsi:type="archimate:DiagramModelArchimateConnection"
        id="23a6c41a"
        source="bab02330"
        target="d31d959f">
      <archimateRelationship
          xsi:type="archimate:FlowRelationship"
          href="FlowRelationship_c1f4b514.xml#c1f4b514"/>
    </sourceConnections>
    <bounds
        x="96"
        y="312"
        width="120"
        height="55"/>
    <archimateElement
        xsi:type="archimate:ApplicationComponent"
        href="ApplicationComponent_1e159d47.xml#1e159d47"/>
  </children>
  <children
      xsi:type="archimate:DiagramModelArchimateObject"
      id="d31d959f"
      targetConnections="23a6c41a">
    <sourceConnections
        xsi:type="archimate:DiagramModelArchimateConnection"
        id="dd404d33"
        source="d31d959f"
        target="20e688a3">
      <archimateRelationship
          xsi:type="archimate:RealizationRelationship"
          href="RealizationRelationship_6269425f.xml#6269425f"/>
    </sourceConnections>
    <sourceConnections
        xsi:type="archimate:DiagramModelArchimateConnection"
        id="4bdc6391"
        source="d31d959f"
        target="159fb85e">
      <archimateRelationship
          xsi:type="archimate:FlowRelationship"
          href="FlowRelationship_ab4ff082.xml#ab4ff082"/>
    </sourceConnections>
    <bounds
        x="96"
        y="399"
        width="120"
        height="55"/>
    <archimateElement
        xsi:type="archimate:ApplicationComponent"
        href="ApplicationComponent_2a15a799.xml#2a15a799"/>
  </children>
  <children
      xsi:type="archimate:DiagramModelArchimateObject"
      id="a997ee02">
    <sourceConnections
        xsi:type="archimate:DiagramModelArchimateConnection"
        id="4b42ea75"
        source="a997ee02"
        target="20e688a3">
      <archimateRelationship
          xsi:type="archimate:RealizationRelationship"
          href="RealizationRelationship_84e8fa59.xml#84e8fa59"/>
    </sourceConnections>
    <bounds
        x="264"
        y="564"
        width="120"
        height="55"/>
    <archimateElement
        xsi:type="archimate:ApplicationComponent"
        href="ApplicationComponent_df53ddb7.xml#df53ddb7"/>
  </children>
  <children
      xsi:type="archimate:DiagramModelArchimateObject"
      id="159fb85e"
      targetConnections="4bdc6391">
    <sourceConnections
        xsi:type="archimate:DiagramModelArchimateConnection"
        id="75bd4aeb"
        source="159fb85e"
        target="20e688a3">
      <archimateRelationship
          xsi:type="archimate:RealizationRelationship"
          href="RealizationRelationship_20e36456.xml#20e36456"/>
    </sourceConnections>
    <bounds
        x="96"
        y="480"
        width="120"
        height="55"/>
    <archimateElement
        xsi:type="archimate:ApplicationComponent"
        href="ApplicationComponent_5af75d9a.xml#5af75d9a"/>
  </children>
  <children
      xsi:type="archimate:DiagramModelArchimateObject"
      id="ef9e41ad"
      targetConnections="1a18c98b 1be32631 0bca3edb 90d152a1"
      type="1">
    <sourceConnections
        xsi:type="archimate:DiagramModelArchimateConnection"
        id="c7f98e8f"
        source="ef9e41ad"
        target="ef680df5">
      <archimateRelationship
          xsi:type="archimate:ServingRelationship"
          href="ServingRelationship_761e1a8f.xml#761e1a8f"/>
    </sourceConnections>
    <bounds
        x="672"
        y="312"
        width="120"
        height="55"/>
    <archimateElement
        xsi:type="archimate:BusinessService"
        href="BusinessService_69732d33.xml#69732d33"/>
  </children>
  <children
      xsi:type="archimate:DiagramModelArchimateObject"
      id="416c04cc">
    <sourceConnections
        xsi:type="archimate:DiagramModelArchimateConnection"
        id="1be32631"
        source="416c04cc"
        target="ef9e41ad">
      <archimateRelationship
          xsi:type="archimate:RealizationRelationship"
          href="RealizationRelationship_95c6d856.xml#95c6d856"/>
    </sourceConnections>
    <bounds
        x="864"
        y="144"
        width="120"
        height="55"/>
    <archimateElement
        xsi:type="archimate:ApplicationComponent"
        href="ApplicationComponent_1762276a.xml#1762276a"/>
  </children>
  <children
      xsi:type="archimate:DiagramModelArchimateObject"
      id="b254741c"
      targetConnections="e1aecf28">
    <sourceConnections
        xsi:type="archimate:DiagramModelArchimateConnection"
        id="0bca3edb"
        source="b254741c"
        target="ef9e41ad">
      <archimateRelationship
          xsi:type="archimate:RealizationRelationship"
          href="RealizationRelationship_e846ad38.xml#e846ad38"/>
    </sourceConnections>
    <bounds
        x="864"
        y="321"
        width="120"
        height="55"/>
    <archimateElement
        xsi:type="archimate:ApplicationComponent"
        href="ApplicationComponent_8226ed8f.xml#8226ed8f"/>
  </children>
  <children
      xsi:type="archimate:DiagramModelArchimateObject"
      id="aa60c550">
    <sourceConnections
        xsi:type="archimate:DiagramModelArchimateConnection"
        id="1a18c98b"
        source="aa60c550"
        target="ef9e41ad">
      <archimateRelationship
          xsi:type="archimate:RealizationRelationship"
          href="RealizationRelationship_f2e41a01.xml#f2e41a01"/>
    </sourceConnections>
    <sourceConnections
        xsi:type="archimate:DiagramModelArchimateConnection"
        id="e1aecf28"
        source="aa60c550"
        target="b254741c">
      <archimateRelationship
          xsi:type="archimate:FlowRelationship"
          href="FlowRelationship_d6e76338.xml#d6e76338"/>
    </sourceConnections>
    <bounds
        x="864"
        y="228"
        width="120"
        height="55"/>
    <archimateElement
        xsi:type="archimate:ApplicationComponent"
        href="ApplicationComponent_bd141740.xml#bd141740"/>
  </children>
  <children
      xsi:type="archimate:DiagramModelArchimateObject"
      id="54d73ee3">
    <sourceConnections
        xsi:type="archimate:DiagramModelArchimateConnection"
        id="c0c006b4"
        source="54d73ee3"
        target="20e688a3">
      <archimateRelationship
          xsi:type="archimate:RealizationRelationship"
          href="RealizationRelationship_18d19a08.xml#18d19a08"/>
    </sourceConnections>
    <bounds
        x="96"
        y="564"
        width="120"
        height="55"/>
    <archimateElement
        xsi:type="archimate:ApplicationComponent"
        href="ApplicationComponent_129e2559.xml#129e2559"/>
  </children>
  <children
      xsi:type="archimate:DiagramModelArchimateObject"
      id="57fc9938">
    <sourceConnections
        xsi:type="archimate:DiagramModelArchimateConnection"
        id="90d152a1"
        source="57fc9938"
        target="ef9e41ad">
      <archimateRelationship
          xsi:type="archimate:RealizationRelationship"
          href="RealizationRelationship_39980fdf.xml#39980fdf"/>
    </sourceConnections>
    <bounds
        x="864"
        y="408"
        width="120"
        height="55"/>
    <archimateElement
        xsi:type="archimate:ApplicationComponent"
        href="ApplicationComponent_129e2559.xml#129e2559"/>
  </children>
  <children
      xsi:type="archimate:DiagramModelArchimateObject"
      id="a243dafb">
    <sourceConnections
        xsi:type="archimate:DiagramModelArchimateConnection"
        id="eb6c2190"
        source="a243dafb"
        target="20e688a3">
      <archimateRelationship
          xsi:type="archimate:RealizationRelationship"
          href="RealizationRelationship_467311a6.xml#467311a6"/>
    </sourceConnections>
    <bounds
        x="96"
        y="156"
        width="120"
        height="55"/>
    <archimateElement
        xsi:type="archimate:ApplicationComponent"
        href="ApplicationComponent_0509a972.xml#0509a972"/>
  </children>
  <children
      xsi:type="archimate:DiagramModelArchimateObject"
      id="f9a55acd">
    <sourceConnections
        xsi:type="archimate:DiagramModelArchimateConnection"
        id="1603d18d"
        source="f9a55acd"
        target="bab02330">
      <archimateRelationship
          xsi:type="archimate:FlowRelationship"
          href="FlowRelationship_7a405056.xml#7a405056"/>
    </sourceConnections>
    <bounds
        x="96"
        y="228"
        width="120"
        height="55"/>
    <archimateElement
        xsi:type="archimate:ApplicationComponent"
        href="ApplicationComponent_2b58b9fc.xml#2b58b9fc"/>
  </children>
</archimate:ArchimateDiagramModel>
